kinopoisk_dev/__init__.py
kinopoisk_dev/abc/__init__.py
kinopoisk_dev/abc/request_abc.py
kinopoisk_dev/exception.py
kinopoisk_dev/fields/__init__.py
kinopoisk_dev/fields/image_field.py
kinopoisk_dev/fields/movie_field.py
kinopoisk_dev/fields/person_field.py
kinopoisk_dev/fields/poss_val_field.py
kinopoisk_dev/fields/review_field.py
kinopoisk_dev/fields/season_field.py
kinopoisk_dev/kinopoisk_dev.py
kinopoisk_dev/model.py
kinopoisk_dev/params/__init__.py
kinopoisk_dev/params/base_params.py
kinopoisk_dev/params/image_params.py
kinopoisk_dev/params/movie_params.py
kinopoisk_dev/params/person_params.py
kinopoisk_dev/params/review_params.py
kinopoisk_dev/params/season_params.py
kinopoisk_dev/request.py
kinopoisk_dev/untils.py
kinopoisk_dev/urls.py
kinopoisk_dev-0.2.0.dist-info/METADATA
kinopoisk_dev-0.2.0.dist-info/WHEEL
kinopoisk_dev-0.2.0.dist-info/RECORD
